{"producto": [

    {"marca":"frugos del valle", "imagen": "https://supermas.cdn1.dattamax.com/userfiles/images/productos/600/96515.png", "material": "carton_lacteos", "codigo_de_barras": "7840058009326"},
    {"marca":"De la costa", "imagen": "https://www.stock.com.py/images/thumbs/0178850.png", "material": "plastico", "codigo_de_barras": "7840981000049"},
    {"marca":"Arcor", "imagen": "https://www.realonline.com.py/media/catalog/product/cache/3f15339c1db7f7a94f5f1d1b7cf2eabf/7/7/7790580717407.jpg", "material": "carton", "codigo_de_barras":"7790580717407" },
    {"marca":"Coca Cola", "imagen": "https://porter.com.py/image/cache/catalog/779/7790895/7790895002748-700x700.jpg.webp", "material": "lata_gaseosa", "codigo_de_barras": "7790895002748"}
 ]}
